django_visual_queries-0.2.dist-info/DESCRIPTION.rst
django_visual_queries-0.2.dist-info/METADATA
django_visual_queries-0.2.dist-info/RECORD
django_visual_queries-0.2.dist-info/WHEEL
django_visual_queries-0.2.dist-info/metadata.json
django_visual_queries-0.2.dist-info/top_level.txt
qb/__init__.py
qb/admin.py
qb/apps.py
qb/features.py
qb/models.py
qb/tests.py
qb/urls.py
qb/views.py
qb/migrations/0001_initial.py
qb/migrations/0002_contact.py
qb/migrations/0003_auto_20180607_1638.py
qb/migrations/0004_auto_20180704_1447.py
qb/migrations/0005_auto_20180704_1840.py
qb/migrations/0006_feature_order_by.py
qb/migrations/0007_feature_order_asc.py
qb/migrations/__init__.py
qb/templates/qb/index.html
