Metadata-Version: 2.0
Name: django-visual-queries
Version: 0.2
Summary: A simple Django app to visually create DB queries.
Home-page: http://www.vusakhoza.cherub.co.zw/
Author: Vusumuzi Khoza
Author-email: vusakhoza@gmail.com
License: BSD License
Platform: UNKNOWN
Classifier: Environment :: Web Environment
Classifier: Framework :: Django
Classifier: Framework :: Django :: 2.0
Classifier: Intended Audience :: Developers
Classifier: License :: OSI Approved :: BSD License
Classifier: Operating System :: OS Independent
Classifier: Programming Language :: Python
Classifier: Programming Language :: Python :: 3.5
Classifier: Programming Language :: Python :: 3.6
Classifier: Topic :: Internet :: WWW/HTTP
Classifier: Topic :: Internet :: WWW/HTTP :: Dynamic Content
